iudex/__init__.py
iudex/asgi.py
iudex/config.py
iudex/django/__init__.py
iudex/django/package.py
iudex/django/utils.py
iudex/fastapi.py
iudex/instrumentation.py
iudex/monkeypatches/clean_attribute.py
iudex/monkeypatches/encode_value.py
iudex/monkeypatches/get_attributes.py
iudex/monkeypatches/logging.py
iudex/monkeypatches/print.py
iudex/openai/__init__.py
iudex/openai/shared/__init__.py
iudex/openai/shared/chat_wrappers.py
iudex/openai/shared/completion_wrappers.py
iudex/openai/shared/config.py
iudex/openai/shared/embeddings_wrappers.py
iudex/openai/shared/image_gen_wrappers.py
iudex/openai/utils.py
iudex/openai/v0/__init__.py
iudex/openai/v1/__init__.py
iudex/openai/v1/assistant_wrappers.py
iudex/openai/v1/event_handler_wrapper.py
iudex/openai/version.py
iudex/supabase/__init__.py
iudex/supabase/package.py
iudex/supabase/utils.py
iudex/trace.py
iudex/utils.py
iudex-0.15.4.dist-info/LICENSE
iudex-0.15.4.dist-info/METADATA
iudex-0.15.4.dist-info/WHEEL
iudex-0.15.4.dist-info/RECORD
