Metadata-Version: 2.1
Name: iudex
Version: 0.15.4
Summary: 
Author: Drake Wong
Author-email: drake@iudex.ai
Requires-Python: >=3.9, !=2.7.*, !=3.0.*, !=3.1.*, !=3.2.*, !=3.3.*, !=3.4.*, !=3.5.*, !=3.6.*, !=3.7.*, !=3.8.*
Classifier: Programming Language :: Python :: 3
Classifier: Programming Language :: Python :: 3.9
Classifier: Programming Language :: Python :: 3.10
Classifier: Programming Language :: Python :: 3.11
Classifier: Programming Language :: Python :: 3.12
Requires-Dist: opentelemetry-contrib-instrumentations (>=0.48b0,<0.49)
Requires-Dist: opentelemetry-exporter-otlp (>=1.27.0,<2.0.0)
Requires-Dist: opentelemetry-instrumentation-alephalpha (>=0.32.1,<0.33.0)
Requires-Dist: opentelemetry-instrumentation-anthropic (>=0.32.1,<0.33.0)
Requires-Dist: opentelemetry-instrumentation-bedrock (>=0.32.1,<0.33.0)
Requires-Dist: opentelemetry-instrumentation-chromadb (>=0.32.1,<0.33.0)
Requires-Dist: opentelemetry-instrumentation-cohere (>=0.32.1,<0.33.0)
Requires-Dist: opentelemetry-instrumentation-google-generativeai (>=0.32.1,<0.33.0)
Requires-Dist: opentelemetry-instrumentation-haystack (>=0.32.1,<0.33.0)
Requires-Dist: opentelemetry-instrumentation-langchain (>=0.32.1,<0.33.0)
Requires-Dist: opentelemetry-instrumentation-llamaindex (>=0.32.1,<0.33.0)
Requires-Dist: opentelemetry-instrumentation-milvus (>=0.32.1,<0.33.0)
Requires-Dist: opentelemetry-instrumentation-mistralai (>=0.32.1,<0.33.0)
Requires-Dist: opentelemetry-instrumentation-ollama (>=0.32.1,<0.33.0)
Requires-Dist: opentelemetry-instrumentation-pinecone (>=0.32.1,<0.33.0)
Requires-Dist: opentelemetry-instrumentation-qdrant (>=0.32.1,<0.33.0)
Requires-Dist: opentelemetry-instrumentation-replicate (>=0.32.1,<0.33.0)
Requires-Dist: opentelemetry-instrumentation-together (>=0.32.1,<0.33.0)
Requires-Dist: opentelemetry-instrumentation-transformers (>=0.32.1,<0.33.0)
Requires-Dist: opentelemetry-instrumentation-vertexai (>=0.32.1,<0.33.0)
Requires-Dist: opentelemetry-instrumentation-watsonx (>=0.32.1,<0.33.0)
Requires-Dist: opentelemetry-instrumentation-weaviate (>=0.32.1,<0.33.0)
Requires-Dist: tiktoken (>=0.3.3,<1)
Requires-Dist: wrapt (>=1.16.0,<2.0.0)
